generator
parser
tests
