Metadata-Version: 2.1
Name: graph-json-generator
Version: 0.0.52
Summary: Transforming any data sources into graphs in JSON format
Home-page: https://github.com/QubitPi/Antiqua/tree/master/graph-json-generator
Author: Jiaqi Liu
Author-email: jack20220723@gmail.com
License: Apache-2.0
Requires-Python: >=3.10
